README.rst
setup.py
manci/XRootD.py
manci/__init__.py
manci/__main__.py
manci/data_lookup.py
manci/data_management.py
manci/exceptions.py
manci/structures.py
manci/utils.py
manci/version.py
manci.egg-info/PKG-INFO
manci.egg-info/SOURCES.txt
manci.egg-info/dependency_links.txt
manci.egg-info/requires.txt
manci.egg-info/top_level.txt
manci/templates/get_job_from_ganga.py