Metadata-Version: 1.1
Name: manci
Version: 0.0.6
Summary: Access and manage data in DIRAC
Home-page: https://github.com/chrisburr/manci
Author: Chris Burr
Author-email: c.b@cern.ch
License: BSD 3-clause
Download-URL: https://github.com/chrisburr/manci/releases
Platform: UNKNOWN
Classifier: Development Status :: 2 - Pre-Alpha
Classifier: Intended Audience :: Developers
Classifier: Intended Audience :: Information Technology
Classifier: Intended Audience :: Science/Research
Classifier: License :: OSI Approved :: BSD License
Classifier: Operating System :: Unix
Classifier: Programming Language :: Python
Classifier: Programming Language :: Python :: 2.7
Classifier: Topic :: Scientific/Engineering :: Physics
Classifier: Topic :: Utilities
